flask_login_saml/__init__.py
flask_login_saml/client.py
flask_login_saml/user.py
flask_login_saml-1.0.11.dist-info/LICENSE
flask_login_saml-1.0.11.dist-info/METADATA
flask_login_saml-1.0.11.dist-info/WHEEL
flask_login_saml-1.0.11.dist-info/top_level.txt
flask_login_saml-1.0.11.dist-info/RECORD
